{
    "type": "generic",
    "pools": [
        {
            "rolls": 1,
            "entries": [
                {
                    "type": "item",
                    "name": "debug_stick",
                    "functions": [
                        {
                            "function": "set_lore",
                            "entity": "this",
                            "lore": [
                                [
                                    {
                                        "text": "",
                                        "italic": false,
                                        "color": "dark_gray"
                                    },
                                    {
                                        "storage": "asset:define",
                                        "nbt": "sys.used[0]",
                                        "interpret": true
                                    },
                                    {
                                        "text": " "
                                    },
                                    {
                                        "storage": "asset:define",
                                        "nbt": "sys.used[1]",
                                        "interpret": true
                                    },
                                    {
                                        "text": " "
                                    },
                                    {
                                        "storage": "asset:define",
                                        "nbt": "sys.used[2]",
                                        "interpret": true
                                    },
                                    {
                                        "text": " "
                                    },
                                    {
                                        "storage": "asset:define",
                                        "nbt": "sys.used[3]",
                                        "interpret": true
                                    },
                                    {
                                        "text": " "
                                    },
                                    {
                                        "storage": "asset:define",
                                        "nbt": "sys.used[4]",
                                        "interpret": true
                                    }
                                ]
                            ]
                        }
                    ]
                }
            ]
        }
    ]
}